deconvoluted/__init__.py
deconvoluted/conventions.py
deconvoluted/transforms.py
deconvoluted-0.1.1.dist-info/AUTHORS.rst
deconvoluted-0.1.1.dist-info/LICENSE
deconvoluted-0.1.1.dist-info/METADATA
deconvoluted-0.1.1.dist-info/WHEEL
deconvoluted-0.1.1.dist-info/top_level.txt
deconvoluted-0.1.1.dist-info/RECORD
