Metadata-Version: 2.1
Name: deconvoluted
Version: 0.1.1
Summary: Deconvoluted makes performing integral transforms simple and pythonic!
Home-page: https://github.com/tbuli/deconvoluted
Author: Martin Roelfs
Author-email: martin.roelfs@kuleuven.be
License: MIT license
Keywords: deconvoluted
Platform: UNKNOWN
Classifier: Development Status :: 2 - Pre-Alpha
Classifier: Intended Audience :: Developers
Classifier: License :: OSI Approved :: MIT License
Classifier: Natural Language :: English
Classifier: Programming Language :: Python :: 3
Classifier: Programming Language :: Python :: 3.5
Classifier: Programming Language :: Python :: 3.6
Classifier: Programming Language :: Python :: 3.7
Requires-Dist: numpy
